{
  "cli": {
    "version": ">= 7.0.0",
    "appVersionSource": "local"
  },
  "build": {
    "development": {
      "developmentClient": true,
      "distribution": "internal",
      "channel": "development",
      "env": {
        "EXPO_PUBLIC_API_BASE_URL": "https://staging.mamacare-production-18fc.up.railway.app",
        "EXPO_PUBLIC_VOICE_ENABLED": "true",
        "EXPO_PUBLIC_CHW_DASHBOARD_ENABLED": "true"
      },
      "ios": {
        "simulator": false,
        "resourceClass": "m1-medium"
      },
      "android": {
        "buildType": "apk",
        "resourceClass": "medium"
      }
    },
    "staging": {
      "distribution": "internal",
      "channel": "staging",
      "env": {
        "EXPO_PUBLIC_API_BASE_URL": "https://staging.mamacare-production-18fc.up.railway.app"
      },
      "ios": {
        "resourceClass": "m1-medium"
      },
      "android": {
        "buildType": "apk",
        "resourceClass": "medium"
      }
    },
    "production": {
      "distribution": "store",
      "channel": "production",
      "env": {
        "EXPO_PUBLIC_API_BASE_URL": "https://mamacare-production-18fc.up.railway.app"
      },
      "ios": {
        "resourceClass": "m1-medium"
      },
      "android": {
        "buildType": "app-bundle",
        "resourceClass": "medium"
      },
      "autoIncrement": true

    },
    "pilot": {
      "distribution": "internal",
      "channel": "pilot",
      "android": {
        "buildType": "apk",
        "resourceClass": "medium",
        "gradleCommand": ":app:assembleRelease"
      },
      "env": {
        "EXPO_PUBLIC_API_BASE_URL": "https://mamacare-production-18fc.up.railway.app",
        "EXPO_PUBLIC_VOICE_ENABLED": "true",
        "EXPO_PUBLIC_USSD_ENABLED": "true",
        "EXPO_PUBLIC_CHW_DASHBOARD_ENABLED": "false",
        "NODE_ENV": "production"
      }
    }
  },
  "submit": {
    "production": {
      "ios": {
        "appleId": "YOUR_APPLE_ID@example.com",
        "ascAppId": "YOUR_APP_STORE_CONNECT_APP_ID",
        "appleTeamId": "YOUR_APPLE_TEAM_ID"
      },
      "android": {
        "serviceAccountKeyPath": "./google-play-service-account.json",
        "track": "internal"
      }
    }
  }
}
